LICENSE.txt
README.md
setup.cfg
setup.py
pyrgasp/__init__.py
pyrgasp/functions.py
pyrgasp/rgasp.py
pyrgasp.egg-info/PKG-INFO
pyrgasp.egg-info/SOURCES.txt
pyrgasp.egg-info/dependency_links.txt
pyrgasp.egg-info/not-zip-safe
pyrgasp.egg-info/requires.txt
pyrgasp.egg-info/top_level.txt